md2ghost/__init__.py
md2ghost/__main__.py
md2ghost-0.0.7.dist-info/LICENSE
md2ghost-0.0.7.dist-info/METADATA
md2ghost-0.0.7.dist-info/WHEEL
md2ghost-0.0.7.dist-info/top_level.txt
md2ghost-0.0.7.dist-info/RECORD
